vi/__init__.py
vi/_static.py
vi/agent.py
vi/config.py
vi/metrics.py
vi/proximity.py
vi/py.typed
vi/replay.py
vi/simulation.py
vi/util.py
violet_simulator-0.3.1.dist-info/WHEEL
violet_simulator-0.3.1.dist-info/METADATA
violet_simulator-0.3.1.dist-info/RECORD
