Metadata-Version: 2.4
Name: violet-simulator
Version: 0.3.1
Summary: A smol simulator framework built on top of PyGame
Author: Storm Timmermans
Author-email: Storm Timmermans <stormtimmermans@icloud.com>
License-Expression: MIT
Requires-Dist: pygame~=2.6
Requires-Dist: polars~=1.2
Requires-Python: >=3.13
Project-URL: documentation, https://api.violet.m-rots.com/vi
Project-URL: homepage, https://violet.m-rots.com
Project-URL: repository, https://github.com/m-rots/violet
